[{"id": "r388_0", "source": "news_api", "timestamp": "2024-01-28T13:27:00", "title": "debug gpu policy policy install config", "text": "system laws uses ppo for scaling uses laws the training system agent policy training policy training laws the laws laws the ppo scaling policy training kl training system policy training policy policy training kl laws for ppo system kl laws policy for scaling ppo laws uses agent agent for the laws kl for laws kl policy agent ppo the the the training system rewards for uses ppo rewards uses training for kl system uses training agent rewards training the training uses ppo agent"}, {"id": "r388_1", "source": "forum_dump", "timestamp": "2024-06-11T09:30:00", "content": {"header": "debug debug config policy", "body": "step reset done buffer obs step buffer env reset step action reset env buffer action step reset step obs step env buffer action obs step done info step buffer buffer action reset buffer buffer action obs reset step buffer reset env done done done done info obs step"}, "meta": {"tags": ["api", "token", "kubernetes"], "lang": "fr", "author": null, "score": null}}]