{"id": "r577_0", "source": "partner_feed", "timestamp": "2024-01-30T17:30:00", "docs": [{"t": "H2", "v": "rlhf env ppo kl grad grad ppo"}, {"t": "H1", "v": "dpo ppo ppo grad rlhf ppo token token env env rlhf env token grad grad dpo"}]}
{"id": "r577_1", "source": "legacy_csv_ingest", "timestamp": "2024-03-22T20:06:00", "docs": [{"t": "H1", "v": "rlhf ppo token env token token"}, {"t": "H1", "v": "rlhf token loss loss ppo env"}, {"t": "P", "v": "env loss grad env ppo env grad dpo token env rlhf grad grad ppo loss env"}, {"t": "H1", "v": "ppo loss ppo reset grad grad token env"}]}
{"id": "r577_2", "source": "helpdesk_export", "timestamp": "2024-06-02T02:47:00", "meta": [{"k": "tag", "v": "k8s"}, {"k": "tag", "v": "windows"}, {"k": "tag", "v": "eval"}], "title": "dagster pipelines spark pipelines infra"}
{"id": "r577_3", "source": "helpdesk_export", "timestamp": "2024-03-14T02:23:00", "content": {"header": "reward agent reward debug", "body": "buffer obs env info env done done action buffer buffer step buffer done obs env buffer info info action obs action info action info step buffer obs reset env env done buffer env"}, "meta": {"tags": ["eval", "k8s", "kubernetes", "safety"], "lang": "en", "author": "jordan", "score": null}}
