{"id": "r337_0", "source": "helpdesk_export", "timestamp": "2024-05-23T05:17:00", "title": "config guide install policy gpu quick", "text": "for for laws laws agent rewards policy rewards scaling rewards policy system agent rewards rewards agent kl uses kl policy scaling laws ppo laws ppo rewards rewards system for uses scaling rewards training agent laws the policy ppo policy laws policy the ppo kl scaling rewards agent policy scaling policy"}
{"id": "dup_29", "source": "forum_dump", "timestamp": "2024-03-14T15:26:00", "docs": [{"t": "H2", "v": "grad reset rlhf reset reset dpo kl reset grad grad rlhf token kl token reset ppo kl loss"}]}
{"id": "r337_2", "source": "news_api", "timestamp": "2024-01-14T01:05:00", "content": {"header": "policy config reward agent", "body": "buffer step buffer env info reset info action step reset obs obs step done info reset done env action buffer buffer reset step step obs env reset obs action action action done obs action action done info action buffer env action step obs buffer step done done action buffer info buffer info info action buffer env buffer buffer done buffer info env action info info buffer step buffer reset step buffer action info action obs buffer step info obs reset action buffer"}, "meta": {"tags": ["install", "safety"], "lang": "de", "author": "riley", "score": null}}
