{"id": "r275_0", "source": "helpdesk_export", "timestamp": "2024-03-08T01:39:00", "meta": [{"k": "tag", "v": "infra"}, {"k": "tag", "v": "kubernetes"}], "title": "spark k8s dagster k8s pipelines"}
{"id": "r275_1", "source": "helpdesk_export", "timestamp": "2024-05-09T04:49:00", "title": "quick guide policy debug install install", "text": "agent rewards laws policy uses ppo the system agent the agent rewards the ppo for agent training scaling policy for scaling system kl policy scaling training uses agent system ppo for agent scaling policy agent policy ppo laws ppo rewards system the ppo policy laws the system scaling system training training uses system training rewards agent scaling ppo training kl scaling rewards kl ppo rewards scaling rewards the agent agent for ppo agent for for kl scaling rewards agent agent scaling scaling laws training"}
