{"id": "k248_0", "lang": "py", "source": "doc_sample", "code": "def f42(a):\\n    if a>0:\\n        a-=1\\n    for i in range(3):\\n        a+=i\\n    while a<5:\\n        break\\n    sorted(a)\\n    map(a)\\n    return a\\ndef f983(a):\\n    map(a)\\n    yaml.load(a)\\n    range(a)\\n    return a\\ndef f451(a):\\n    if a>0:\\n        a-=1\\n    for i in range(3):\\n        a+=i\\n    map(a)\\n    sum(a)\\n    return a\\n"}
{"id": "k248_1", "lang": "py", "source": "repo_A", "code": "def f598(a):\\n    if a>0:\\n        a-=1\\n    len(a)\\n    json.dumps(a)\\n    len(a)\\n    return a\\n"}
