[{"id": "k731_0", "lang": "py", "source": "doc_sample", "code": "def f300(a):\\n    if a>0:\\n        a-=1\\n    for i in range(3):\\n        a+=i\\n    while a<5:\\n        break\\n    return a\\ndef f664(a):\\n    for i in range(3):\\n        a+=i\\n    json.dumps(a)\\n    return a\\ndef f733(a):\\n    for i in range(3):\\n        a+=i\\n    while a<5:\\n        break\\n    sum(a)\\n    range(a)\\n    pickle.loads(a)\\n    return a\\n"}, {"id": "k731_1", "lang": "js", "source": "gen_example", "code": "function add(a,b){return a+b;}\\n"}]