[{"id": "k435_0", "lang": "py", "source": "repo_A", "code": "def f313(a):\\n    if a>0:\\n        a-=1\\n    yaml.load(a)\\n    sum(a)\\n    return a\\ndef f397(a):\\n    map(a)\\n    return a\\ndef f814(a):\\n    if a>0:\\n        a-=1\\n    for i in range(3):\\n        a+=i\\n    sum(a)\\n    sum(a)\\n    return a\\n"}, {"id": "k435_1", "lang": "py", "source": "gen_example", "code": "def f793(a):\\n    for i in range(3):\\n        a+=i\\n    pickle.loads(a)\\n    return a\\ndef f833(a):\\n    if a>0:\\n        a-=1\\n    while a<5:\\n        break\\n    map(a)\\n    len(a)\\n    return a\\n"}]